boxtest/__init__.py
boxtest/test.py
boxtest-0.3.1.dist-info/LICENSE
boxtest-0.3.1.dist-info/METADATA
boxtest-0.3.1.dist-info/WHEEL
boxtest-0.3.1.dist-info/top_level.txt
boxtest-0.3.1.dist-info/RECORD
